KratosMultiphysics/SwimmingDEMApplication/AnalyticTestFactory.py
KratosMultiphysics/SwimmingDEMApplication/BackwardCouplingTestFactory.py
KratosMultiphysics/SwimmingDEMApplication/CFD_DEM_coupling.py
KratosMultiphysics/SwimmingDEMApplication/CandelierTestFactory.py
KratosMultiphysics/SwimmingDEMApplication/DEM_coupled_fluid_dynamics_analysis.py
KratosMultiphysics/SwimmingDEMApplication/DEM_coupled_pfem_fluid_dynamics_analysis.py
KratosMultiphysics/SwimmingDEMApplication/Derivatives.py
KratosMultiphysics/SwimmingDEMApplication/DragTestFactory.py
KratosMultiphysics/SwimmingDEMApplication/FluidDEMTestFactory.py
KratosMultiphysics/SwimmingDEMApplication/GentleInjectionAndErasureTestFactory.py
KratosMultiphysics/SwimmingDEMApplication/InterpolationTestFactory.py
KratosMultiphysics/SwimmingDEMApplication/KratosSwimmingDEMAnalysis.py
KratosMultiphysics/SwimmingDEMApplication/KratosSwimmingDEMPFEMAnalysis.py
KratosMultiphysics/SwimmingDEMApplication/L2_error_calculator_utility.py
KratosMultiphysics/SwimmingDEMApplication/NightTests.py
KratosMultiphysics/SwimmingDEMApplication/PeriodicBackwardCouplingTestFactory.py
KratosMultiphysics/SwimmingDEMApplication/PorosityTestFactory.py
KratosMultiphysics/SwimmingDEMApplication/SPFEMTestFactory.py
KratosMultiphysics/SwimmingDEMApplication/SmallTests.py
KratosMultiphysics/SwimmingDEMApplication/ValidationTests.py
KratosMultiphysics/SwimmingDEMApplication/__init__.py
KratosMultiphysics/SwimmingDEMApplication/analytics.py
KratosMultiphysics/SwimmingDEMApplication/apply_custom_body_force_process.py
KratosMultiphysics/SwimmingDEMApplication/apply_hyperbolic_tangential_porosity_solution_and_body_force_process.py
KratosMultiphysics/SwimmingDEMApplication/apply_hyperbolic_tangential_porosity_solution_transient_body_force_process.py
KratosMultiphysics/SwimmingDEMApplication/apply_porosity_solution_and_body_force_process.py
KratosMultiphysics/SwimmingDEMApplication/apply_porosity_solution_body_force_process.py
kratosswimmingdemapplication-10.4.0.dist-info/METADATA
kratosswimmingdemapplication-10.4.0.dist-info/WHEEL
kratosswimmingdemapplication-10.4.0.dist-info/RECORD
